{
    "features": [
        "Basic",
        "Count_past_visit",
        "Count_future_visit",
        "Timedelta_past_visit",
        "Timedelta_future_visit",
        "VisitNumber_corrected",
        "Count_past_hits_pageviews",
        "Count_future_hits_pageviews"
    ],
    "cv": {
        "method": "GroupKFold"
    },
    "model": {
        "name": "lightgbm",
        "model_params": {
            "boosting_type": "gbdt",
            "objective": "regression",
            "metric": "rmse",
            "learning_rate": 0.1,
            "num_leaves": 100,
            "max_depth": 8,
            "min_child_samples": 100,
            "max_bin": 100,
            "subsample": 0.7,
            "subsample_freq": 1,
            "colsample_bytree": 0.5,
            "seed": 71,
            "bagging_seed": 71,
            "feature_fraction_seed": 71,
            "drop_seed": 71,
            "verbose": -1
        },
        "train_params": {
            "num_boost_round": 350,
            "early_stopping_rounds": 50,
            "verbose_eval": 50
        }
    },
    "dataset": {
        "input_directory": "data/input/",
        "intermediate_directory": "data/interim/",
        "feature_directory": "data/feature/",
        "output_directory": "data/output/",
        "files": {
            "train": "train.ftr",
            "test": "test.ftr"
        }
    },
    "pre_processing": {
        "down_sampling": {
            "enabled": false,
            "bagging_size": 1,
            "random_state": 71
        },
        "getdata_bounces_notnull": {
            "enabled": false
        }
    },
    "post_processing": {
        "bounces_process": {
            "enabled": true
        }
    },
    "args": {
        "config": "configs/lightgbm_12.json",
        "debug_mode": false,
        "force": false,
        "out": "output_0"
    },
    "evals_result_session": {
        "oof_score": 1.5543110653739878,
        "best_iteration": 104.6,
        "n_features": 160,
        "categorical_features": [
            "channelGrouping",
            "device.deviceCategory",
            "device.browser",
            "device.operatingSystem",
            "trafficSource.adContent",
            "trafficSource.adwordsClickInfo.adNetworkType",
            "trafficSource.adwordsClickInfo.gclId",
            "trafficSource.adwordsClickInfo.page",
            "trafficSource.adwordsClickInfo.slot",
            "trafficSource.campaign",
            "trafficSource.keyword",
            "trafficSource.medium",
            "trafficSource.referralPath",
            "trafficSource.source",
            "trafficSource.adwordsClickInfo.isVideoAd",
            "trafficSource.isTrueDirect",
            "geoNetwork.city",
            "geoNetwork.continent",
            "geoNetwork.country",
            "geoNetwork.metro",
            "geoNetwork.networkDomain",
            "geoNetwork.region",
            "geoNetwork.subContinent"
        ],
        "feature_importance": {
            "totals.pageviews": 1833981.6526801556,
            "geoNetwork.country": 434035.8360677719,
            "totals.hits": 344498.43662759213,
            "hits_pageviews_ratio": 307301.61588652804,
            "geoNetwork.city": 220990.44589581192,
            "hits_pageviews_ratio_future7": 124307.69509845079,
            "visitStartTime": 106817.42157558203,
            "device.operatingSystem": 103954.23892646581,
            "trafficSource.referralPath": 101852.96442367062,
            "hits_pageviews_ratio_past30": 95995.92019303922,
            "geoNetwork.networkDomain": 93212.8202512607,
            "channelGrouping": 89832.69419761599,
            "Timedelta_past_visit": 83068.02022179619,
            "hits_sum_past30": 77280.00613828152,
            "geoNetwork.continent": 69201.65182480813,
            "visitNumber_corrected": 69067.60405129493,
            "hits_pageviews_ratio_future14": 60134.20164711475,
            "totals.bounces": 51956.227954600006,
            "hits_pageviews_ratio_past14": 50716.30855206549,
            "hits_pageviews_ratio_future3": 46834.7238743186,
            "hits_pageviews_ratio_future1": 45198.09573145509,
            "geoNetwork.region": 43054.994180370864,
            "sum_hits_pageviews_ratio_per_hour": 40116.13153897971,
            "Timedelta_future_visit": 39673.15944800973,
            "device.isMobile": 37653.83874604404,
            "pageviews_sum_past30": 35287.13082748801,
            "hits_sum_past14": 30732.310166180134,
            "date_hour": 28652.28075292278,
            "visitNumber": 28279.733326268197,
            "hits_sum_future1": 27980.31966688633,
            "hits_pageviews_ratio_future30": 27968.12325068116,
            "geoNetwork.subContinent": 26449.77385764122,
            "hits_pageviews_ratio_past3": 24510.042014178634,
            "geoNetwork.metro": 23932.492304986714,
            "hits_pageviews_ratio_past1": 23075.93454063833,
            "sum_hits_per_hour": 20774.966659246384,
            "hits_pageviews_ratio_past7": 20705.388471916318,
            "hits_sum_past1": 20243.023682823776,
            "trafficSource.isTrueDirect": 19679.334778591245,
            "sum_hits_per_month": 19589.824361896513,
            "device.deviceCategory": 19295.241802460096,
            "sum_hits_per_weekofyear": 19083.38680624664,
            "date_dayofyear": 18022.573574920792,
            "trafficSource.medium": 17243.490676379202,
            "hits_sum_future14": 15151.950254201889,
            "sum_pageviews_per_hour": 14702.58527472036,
            "hits_sum_future30": 14524.3183940202,
            "mean_pageviews_per_weekofyear": 14263.1302409729,
            "pageviews_sum_future1": 14136.839810848236,
            "sum_hits_pageviews_ratio_per_dayofyear": 13956.32093891512,
            "sum_pageviews_per_dayofyear": 13920.458946423232,
            "sum_hits_pageviews_ratio_per_weekofyear": 13620.780489207351,
            "sum_hits_per_dayofyear": 13441.42843279466,
            "date_weekofyear": 13372.566850746516,
            "mean_hits_per_dayofyear": 12893.719601864368,
            "pageviews_sum_future30": 12695.799899351598,
            "mean_hits_per_month": 12633.825621929765,
            "count_past30_visit": 12521.713235400515,
            "pageviews_sum_past14": 12410.089787617326,
            "sum_hits_pageviews_ratio_per_day": 12356.744935975225,
            "hits_sum_past7": 12201.430609983207,
            "pageviews_sum_past7": 12193.918157434464,
            "mean_hits_per_hour": 11649.476228529045,
            "mean_hits_per_day": 11433.214919631742,
            "pageviews_sum_past1": 11418.758658647537,
            "mean_hits_pageviews_ratio_per_dayofyear": 11354.257297846005,
            "hits_sum_future7": 10987.202219462395,
            "sum_pageviews_per_weekofyear": 10823.838106208295,
            "mean_hits_per_weekofyear": 10736.794017551094,
            "mean_pageviews_per_dayofyear": 10692.513964020554,
            "pageviews_sum_future7": 10185.950692844392,
            "hits_sum_past3": 9707.092724514008,
            "hits_sum_future3": 9685.016599285602,
            "date_day": 9347.040790756791,
            "sum_hits_per_day": 9289.492551629246,
            "totals.newVisits": 9238.371723674614,
            "mean_hits_pageviews_ratio_per_weekofyear": 9208.397735998244,
            "count_future1_visit": 9025.05949434042,
            "mean_pageviews_per_day": 8678.696747338772,
            "pageviews_sum_future14": 8605.903798532487,
            "date_dayofweek": 8271.277116823196,
            "pageviews_sum_past3": 8153.429535996914,
            "mean_hits_pageviews_ratio_per_hour": 7998.7726614696685,
            "sum_pageviews_per_month": 7358.0334378145635,
            "mean_pageviews_per_hour": 7293.70757856667,
            "trafficSource.keyword": 7287.61130131185,
            "sum_hits_per_quarter": 6934.106301498413,
            "mean_hits_pageviews_ratio_per_day": 6827.060554759053,
            "sum_pageviews_per_quarter": 6584.79519399515,
            "pageviews_sum_future3": 6097.9578944325895,
            "sum_pageviews_per_day": 6077.244612318277,
            "trafficSource.source": 6009.322696241737,
            "count_past14_visit": 4889.610305404663,
            "mean_pageviews_per_month": 4286.349894445329,
            "count_future30_visit": 4249.978872847557,
            "mean_hits_per_dayofweek": 4207.947000460326,
            "networkDomain_notset": 4146.4884436570355,
            "mean_hits_per_quarter": 4092.408910369873,
            "visitNumber_diff": 3544.555061721802,
            "count_future7_visit": 3542.1495507240297,
            "date_month": 3511.8868795961143,
            "sum_hits_per_dayofweek": 3506.995923361182,
            "mean_hits_pageviews_ratio_per_quarter": 3436.0061655252766,
            "count_future14_visit": 3321.710827064514,
            "mean_hits_pageviews_ratio_per_month": 3313.5093485295774,
            "median_hits_per_weekofyear": 3304.038245201111,
            "count_future3_visit": 3070.700759404898,
            "device.browser": 2889.662232875824,
            "count_past7_visit": 2593.985662436485,
            "mean_pageviews_per_dayofweek": 2498.5817154720426,
            "sum_pageviews_per_dayofweek": 2127.4883709415794,
            "sum_hits_pageviews_ratio_per_month": 2032.1070998549462,
            "median_pageviews_per_day": 2031.7087106376887,
            "mean_hits_pageviews_ratio_per_dayofweek": 1969.8759746551514,
            "date_year": 1897.5560054779053,
            "sum_hits_pageviews_ratio_per_dayofweek": 1789.7094675764442,
            "median_pageviews_per_dayofyear": 1742.0866419807076,
            "mean_hits_per_year": 1549.6517700195313,
            "count_past1_visit": 1538.733532643318,
            "median_pageviews_per_month": 1504.6342573963107,
            "median_hits_pageviews_ratio_per_weekofyear": 1279.4601739168168,
            "count_past3_visit": 1244.0910700321197,
            "median_hits_per_day": 1082.4443969726562,
            "median_hits_per_dayofyear": 1077.838885498047,
            "median_pageviews_per_quarter": 1059.5840632215143,
            "median_hits_per_month": 934.0169911310077,
            "time_delta": 847.7211785793304,
            "median_pageviews_per_weekofyear": 822.7612860471011,
            "mean_pageviews_per_quarter": 809.6691890239715,
            "median_hits_pageviews_ratio_per_day": 676.3980537414551,
            "sum_hits_pageviews_ratio_per_quarter": 339.9882389068604,
            "date_quarter": 306.2041610717773,
            "median_hits_pageviews_ratio_per_dayofyear": 245.3465389251709,
            "median_hits_pageviews_ratio_per_month": 222.28352501243353,
            "median_hits_per_hour": 191.00779724121094,
            "trafficSource.adwordsClickInfo.slot": 187.64339599609374,
            "trafficSource.adwordsClickInfo.page": 142.02659912109374,
            "trafficSource.campaign": 130.90460205078125,
            "mean_hits_pageviews_ratio_per_year": 117.15098037719727,
            "trafficSource.adwordsClickInfo.isVideoAd": 116.747998046875,
            "median_hits_pageviews_ratio_per_hour": 105.55685729980469,
            "median_pageviews_per_hour": 61.47529983520508,
            "sessionId_overlap_flg": 60.986480712890625,
            "median_hits_per_dayofweek": 30.911199951171874,
            "networkDomain_unknown": 0.0004834140185266733,
            "networkDomain_voxilitycom": 0.0,
            "sum_hits_per_year": 0.0,
            "median_hits_per_quarter": 0.0,
            "median_hits_pageviews_ratio_per_quarter": 0.0,
            "sum_hits_pageviews_ratio_per_year": 0.0,
            "sum_pageviews_per_year": 0.0,
            "median_hits_pageviews_ratio_per_dayofweek": 0.0,
            "median_pageviews_per_dayofweek": 0.0,
            "median_hits_pageviews_ratio_per_year": 0.0,
            "median_pageviews_per_year": 0.0,
            "median_hits_per_year": 0.0,
            "trafficSource.adwordsClickInfo.gclId": 0.0,
            "trafficSource.adwordsClickInfo.adNetworkType": 0.0,
            "mean_pageviews_per_year": 0.0,
            "trafficSource.adContent": 0.0
        }
    },
    "evals_result_user": {
        "oof_score": 1.5433511151796657,
        "best_iteration": 39.2,
        "n_features": 444,
        "feature_importance": {
            "t_sum_act": 1774026.1154567092,
            "t_sum_log": 1485452.8777798533,
            "t_mean": 555624.2378453255,
            "predictions": 339352.26883306506,
            "totals.pageviews": 33795.5964768976,
            "pageviews_sum_future7": 32329.153262329102,
            "t_median": 24843.6069429636,
            "hits_pageviews_ratio": 24677.402933979036,
            "sum_hits_pageviews_ratio_per_hour": 18719.333626484127,
            "pred_1": 18579.24798550606,
            "totals.hits": 15555.315751242637,
            "geoNetwork.country": 15288.789055252075,
            "Timedelta_future_visit": 14530.597024154664,
            "date_day": 14434.73845629692,
            "pred_2": 14353.400566911698,
            "mean_hits_pageviews_ratio_per_day": 13828.078662681579,
            "mean_hits_per_hour": 12415.690942382813,
            "mean_hits_pageviews_ratio_per_hour": 12252.21713848114,
            "Timedelta_past_visit": 12080.627225637436,
            "sum_hits_per_day": 11900.535302734375,
            "date_hour": 11682.841651177407,
            "sum_hits_pageviews_ratio_per_day": 11130.36693983078,
            "mean_pageviews_per_day": 10961.604496100545,
            "pred_4": 10731.094198417664,
            "pred_3": 10616.29042172432,
            "pred_0": 10369.66125588417,
            "sum_hits_per_hour": 9765.283485746384,
            "device.operatingSystem": 9702.987895202637,
            "sum_hits_pageviews_ratio_per_weekofyear": 9621.255951783061,
            "mean_hits_per_day": 9529.462675857543,
            "sum_pageviews_per_hour": 9459.136982297898,
            "mean_hits_pageviews_ratio_per_weekofyear": 9413.573188591003,
            "sum_hits_per_dayofyear": 9392.494285583496,
            "visitStartTime": 9316.614153289795,
            "pageviews_sum_past7": 9153.04801082611,
            "trafficSource.isTrueDirect": 8988.86249704361,
            "pageviews_sum_future30": 8894.61561050415,
            "sum_pageviews_per_dayofyear": 8749.305785942077,
            "pageviews_sum_past30": 8550.862256383896,
            "sum_hits_pageviews_ratio_per_dayofyear": 8457.991575431824,
            "geoNetwork.region": 8448.682944774628,
            "mean_pageviews_per_hour": 8398.3811293602,
            "pageviews_sum_past14": 8342.338320279121,
            "hits_sum_past7": 8304.593594694137,
            "mean_pageviews_per_dayofyear": 8252.634626483918,
            "mean_pageviews_per_weekofyear": 8153.244516372681,
            "date_dayofyear": 8138.223894119263,
            "hits_pageviews_ratio_future30": 8123.057416915894,
            "date_dayofweek": 7933.58256893158,
            "mean_hits_pageviews_ratio_per_dayofyear": 7701.592296409607,
            "mean_hits_per_dayofyear": 7699.613197803497,
            "hits_sum_past14": 7644.97858042717,
            "networkDomain_notset": 7604.98129901886,
            "visitNumber": 7548.524850845337,
            "geoNetwork.networkDomain": 7256.732968711853,
            "hits_sum_past30": 7172.515620428324,
            "hits_pageviews_ratio_past30": 7161.3257524490355,
            "sum_hits_per_weekofyear": 7124.937956047058,
            "pageviews_sum_future14": 7081.385723876953,
            "sum_hits_per_dayofweek": 7051.608304595948,
            "hits_sum_future30": 6842.275966072082,
            "hits_pageviews_ratio_past14": 6749.6999599456785,
            "hits_pageviews_ratio_future1": 6747.773155212402,
            "mean_hits_per_weekofyear": 6572.450206375122,
            "median_pageviews_per_day": 6450.820143890381,
            "trafficSource.referralPath": 6436.998238754272,
            "date_weekofyear": 6424.049866104126,
            "mean_pageviews_per_dayofweek": 6319.740795898438,
            "totals.bounces": 6060.058127403259,
            "mean_hits_per_dayofweek": 6006.222853565216,
            "sum_pageviews_per_weekofyear": 5996.785212898254,
            "totals.newVisits": 5869.7799525260925,
            "sum_pageviews_per_day": 5790.086608886719,
            "hits_pageviews_ratio_future14": 5764.00633392334,
            "hits_pageviews_ratio_past7": 5730.619176149368,
            "geoNetwork.metro": 5711.1340063095095,
            "hits_pageviews_ratio_future7": 5593.705521011352,
            "hits_pageviews_ratio_past1": 5581.972146511078,
            "visitNumber_corrected": 5559.798857688904,
            "trafficSource.keyword": 5437.374406433106,
            "trafficSource.medium": 5429.338612365723,
            "mean_hits_pageviews_ratio_per_dayofweek": 5399.885741615295,
            "hits_pageviews_ratio_past3": 5312.569986343384,
            "hits_sum_future14": 5308.8573598384855,
            "hits_sum_future7": 5278.113813447952,
            "mean_hits_pageviews_ratio_per_month": 5237.968284225464,
            "sum_hits_pageviews_ratio_per_dayofweek": 5116.16835975647,
            "count_past14_visit": 5020.237103271485,
            "sum_hits_per_month": 4896.09808011055,
            "median_hits_per_dayofyear": 4870.022637176514,
            "trafficSource.source": 4651.910015869141,
            "hits_sum_past1": 4426.789576721191,
            "sum_hits_pageviews_ratio_per_month": 4386.614872741699,
            "sum_pageviews_per_month": 4355.059433174133,
            "pageviews_sum_future3": 4292.0171915531155,
            "median_hits_per_weekofyear": 4203.460579681397,
            "sum_pageviews_per_dayofweek": 4066.2873050689695,
            "pageviews_sum_past1": 4061.044741821289,
            "pageviews_sum_past3": 4021.3084120213985,
            "hits_sum_past3": 4008.2102206230165,
            "date_month": 3945.878847694397,
            "geoNetwork.city": 3931.5392421722413,
            "pageviews_sum_future1": 3921.2781147003175,
            "median_hits_pageviews_ratio_per_day": 3843.9075120925904,
            "hits_sum_future3": 3800.392311286926,
            "count_past7_visit": 3739.38677444458,
            "mean_hits_per_month": 3691.6381034851074,
            "mean_pageviews_per_month": 3615.218843841553,
            "channelGrouping": 3600.836183166504,
            "pred_6": 3443.948164367676,
            "median_hits_per_hour": 3416.8563193440436,
            "median_pageviews_per_weekofyear": 3382.459524536133,
            "hits_pageviews_ratio_future3": 3107.439604187012,
            "device.deviceCategory": 3067.2214447021483,
            "hits_sum_future1": 3062.5798189163206,
            "count_future30_visit": 3045.1751243591307,
            "mean_hits_per_quarter": 2967.317670059204,
            "count_future7_visit": 2883.2190124511717,
            "median_hits_per_month": 2751.9704200744627,
            "device.isMobile": 2738.863215637207,
            "median_pageviews_per_month": 2676.445588684082,
            "median_pageviews_per_dayofyear": 2520.406328201294,
            "pred_5": 2450.144526386261,
            "median_pageviews_per_hour": 2444.745725250244,
            "count_past1_visit": 2223.542792510986,
            "mean_pageviews_per_quarter": 2217.2305404663084,
            "count_past30_visit": 2195.177079772949,
            "median_pageviews_per_quarter": 2176.4062994003298,
            "count_past3_visit": 2082.8024839401246,
            "mean_hits_pageviews_ratio_per_quarter": 2025.988452911377,
            "device.browser": 1939.369242811203,
            "median_hits_per_day": 1911.7868507385253,
            "t_nb_sess": 1871.0085441589356,
            "count_future14_visit": 1846.504815673828,
            "median_hits_pageviews_ratio_per_weekofyear": 1774.275308227539,
            "pred_7": 1577.7346639633179,
            "date_quarter": 1570.7334175109863,
            "median_hits_pageviews_ratio_per_dayofyear": 1413.1306785583497,
            "visitNumber_diff": 1337.923388671875,
            "count_future3_visit": 1327.1295845031739,
            "median_hits_pageviews_ratio_per_month": 1248.1905960083009,
            "pred_8": 1187.8780488967896,
            "sum_hits_per_quarter": 1137.1624256134032,
            "pred_9": 1114.270482635498,
            "count_future1_visit": 1108.2973438262939,
            "geoNetwork.continent": 1099.7116832733154,
            "sum_hits_pageviews_ratio_per_quarter": 1085.3565383911132,
            "geoNetwork.subContinent": 1079.2918274879455,
            "networkDomain_unknown": 818.6385410308837,
            "pred_10": 735.8989496469497,
            "sum_pageviews_per_quarter": 691.1499481201172,
            "median_hits_per_dayofweek": 648.9382406234741,
            "pred_13": 647.9805877685546,
            "date_year": 624.0507217407227,
            "median_hits_pageviews_ratio_per_hour": 543.8886428833008,
            "trafficSource.campaign": 406.07444229125974,
            "trafficSource.adwordsClickInfo.gclId": 402.56107864379885,
            "median_hits_pageviews_ratio_per_dayofweek": 309.2849975585938,
            "mean_hits_per_year": 273.7454040527344,
            "trafficSource.adwordsClickInfo.adNetworkType": 266.68560180664065,
            "median_pageviews_per_dayofweek": 253.872998046875,
            "pred_12": 245.19586105346679,
            "trafficSource.adwordsClickInfo.slot": 185.70709953308105,
            "pred_11": 131.13714027404785,
            "sum_pageviews_per_year": 119.331396484375,
            "pred_14": 100.53389892578124,
            "time_delta": 99.57919921875,
            "pred_15": 81.36700134277343,
            "pred_18": 55.59720001220703,
            "trafficSource.adContent": 46.74686126708984,
            "pred_20": 36.35020141601562,
            "pred_25": 30.964199829101563,
            "pred_16": 24.591600036621095,
            "pred_263": 0.0,
            "pred_249": 0.0,
            "trafficSource.adwordsClickInfo.page": 0.0,
            "pred_262": 0.0,
            "pred_261": 0.0,
            "pred_264": 0.0,
            "pred_33": 0.0,
            "pred_250": 0.0,
            "pred_267": 0.0,
            "pred_35": 0.0,
            "pred_34": 0.0,
            "pred_251": 0.0,
            "pred_36": 0.0,
            "pred_37": 0.0,
            "networkDomain_voxilitycom": 0.0,
            "pred_38": 0.0,
            "pred_248": 0.0,
            "pred_39": 0.0,
            "pred_40": 0.0,
            "pred_41": 0.0,
            "pred_260": 0.0,
            "pred_32": 0.0,
            "pred_30": 0.0,
            "pred_31": 0.0,
            "pred_268": 0.0,
            "pred_256": 0.0,
            "pred_269": 0.0,
            "pred_255": 0.0,
            "pred_254": 0.0,
            "pred_27": 0.0,
            "pred_270": 0.0,
            "pred_271": 0.0,
            "pred_253": 0.0,
            "pred_266": 0.0,
            "pred_272": 0.0,
            "pred_273": 0.0,
            "pred_265": 0.0,
            "pred_252": 0.0,
            "pred_274": 0.0,
            "pred_275": 0.0,
            "pred_276": 0.0,
            "pred_277": 0.0,
            "pred_257": 0.0,
            "pred_26": 0.0,
            "pred_28": 0.0,
            "pred_29": 0.0,
            "pred_258": 0.0,
            "trafficSource.adwordsClickInfo.isVideoAd": 0.0,
            "pred_259": 0.0,
            "pred_232": 0.0,
            "pred_42": 0.0,
            "pred_76": 0.0,
            "pred_82": 0.0,
            "pred_81": 0.0,
            "pred_80": 0.0,
            "pred_79": 0.0,
            "pred_78": 0.0,
            "pred_77": 0.0,
            "pred_75": 0.0,
            "pred_84": 0.0,
            "pred_74": 0.0,
            "pred_73": 0.0,
            "pred_72": 0.0,
            "pred_71": 0.0,
            "pred_70": 0.0,
            "pred_69": 0.0,
            "pred_83": 0.0,
            "pred_85": 0.0,
            "pred_43": 0.0,
            "pred_93": 0.0,
            "pred_99": 0.0,
            "pred_98": 0.0,
            "pred_97": 0.0,
            "pred_96": 0.0,
            "pred_95": 0.0,
            "pred_94": 0.0,
            "sessionId_overlap_flg": 0.0,
            "pred_86": 0.0,
            "pred_92": 0.0,
            "pred_91": 0.0,
            "pred_90": 0.0,
            "pred_89": 0.0,
            "pred_88": 0.0,
            "pred_87": 0.0,
            "pred_68": 0.0,
            "pred_67": 0.0,
            "pred_66": 0.0,
            "pred_50": 0.0,
            "pred_54": 0.0,
            "median_hits_per_quarter": 0.0,
            "pred_53": 0.0,
            "median_hits_pageviews_ratio_per_quarter": 0.0,
            "pred_52": 0.0,
            "pred_51": 0.0,
            "pred_49": 0.0,
            "pred_65": 0.0,
            "pred_48": 0.0,
            "pred_246": 0.0,
            "pred_47": 0.0,
            "pred_46": 0.0,
            "pred_45": 0.0,
            "pred_44": 0.0,
            "pred_55": 0.0,
            "pred_56": 0.0,
            "pred_57": 0.0,
            "pred_58": 0.0,
            "pred_59": 0.0,
            "pred_60": 0.0,
            "pred_61": 0.0,
            "pred_62": 0.0,
            "pred_63": 0.0,
            "pred_64": 0.0,
            "sum_hits_pageviews_ratio_per_year": 0.0,
            "sum_hits_per_year": 0.0,
            "median_hits_pageviews_ratio_per_year": 0.0,
            "median_pageviews_per_year": 0.0,
            "median_hits_per_year": 0.0,
            "mean_hits_pageviews_ratio_per_year": 0.0,
            "mean_pageviews_per_year": 0.0,
            "pred_247": 0.0,
            "pred_241": 0.0,
            "pred_245": 0.0,
            "pred_181": 0.0,
            "pred_183": 0.0,
            "pred_184": 0.0,
            "pred_185": 0.0,
            "pred_186": 0.0,
            "pred_187": 0.0,
            "pred_188": 0.0,
            "pred_189": 0.0,
            "pred_19": 0.0,
            "pred_190": 0.0,
            "pred_191": 0.0,
            "pred_192": 0.0,
            "pred_193": 0.0,
            "pred_194": 0.0,
            "pred_195": 0.0,
            "pred_196": 0.0,
            "pred_182": 0.0,
            "pred_180": 0.0,
            "pred_198": 0.0,
            "pred_179": 0.0,
            "pred_165": 0.0,
            "pred_166": 0.0,
            "pred_167": 0.0,
            "pred_168": 0.0,
            "pred_169": 0.0,
            "pred_17": 0.0,
            "pred_170": 0.0,
            "pred_171": 0.0,
            "pred_172": 0.0,
            "pred_173": 0.0,
            "pred_174": 0.0,
            "pred_175": 0.0,
            "pred_176": 0.0,
            "pred_177": 0.0,
            "pred_178": 0.0,
            "pred_197": 0.0,
            "pred_199": 0.0,
            "pred_244": 0.0,
            "pred_216": 0.0,
            "pred_218": 0.0,
            "pred_219": 0.0,
            "pred_22": 0.0,
            "pred_220": 0.0,
            "pred_221": 0.0,
            "pred_222": 0.0,
            "pred_223": 0.0,
            "pred_224": 0.0,
            "pred_225": 0.0,
            "pred_226": 0.0,
            "pred_227": 0.0,
            "pred_228": 0.0,
            "pred_229": 0.0,
            "pred_23": 0.0,
            "pred_230": 0.0,
            "pred_217": 0.0,
            "pred_215": 0.0,
            "pred_233": 0.0,
            "pred_214": 0.0,
            "pred_200": 0.0,
            "pred_201": 0.0,
            "pred_202": 0.0,
            "pred_203": 0.0,
            "pred_204": 0.0,
            "pred_205": 0.0,
            "pred_206": 0.0,
            "pred_207": 0.0,
            "pred_208": 0.0,
            "pred_209": 0.0,
            "pred_21": 0.0,
            "pred_210": 0.0,
            "pred_211": 0.0,
            "pred_212": 0.0,
            "pred_213": 0.0,
            "pred_164": 0.0,
            "pred_163": 0.0,
            "pred_162": 0.0,
            "pred_107": 0.0,
            "pred_109": 0.0,
            "pred_110": 0.0,
            "pred_111": 0.0,
            "pred_112": 0.0,
            "pred_113": 0.0,
            "pred_114": 0.0,
            "pred_115": 0.0,
            "pred_116": 0.0,
            "pred_117": 0.0,
            "pred_118": 0.0,
            "pred_119": 0.0,
            "pred_120": 0.0,
            "pred_121": 0.0,
            "pred_122": 0.0,
            "pred_123": 0.0,
            "pred_108": 0.0,
            "pred_106": 0.0,
            "pred_161": 0.0,
            "pred_105": 0.0,
            "pred_243": 0.0,
            "pred_242": 0.0,
            "pred_231": 0.0,
            "pred_240": 0.0,
            "pred_24": 0.0,
            "pred_239": 0.0,
            "pred_238": 0.0,
            "pred_237": 0.0,
            "pred_236": 0.0,
            "pred_235": 0.0,
            "pred_100": 0.0,
            "pred_101": 0.0,
            "pred_102": 0.0,
            "pred_103": 0.0,
            "pred_104": 0.0,
            "pred_124": 0.0,
            "pred_125": 0.0,
            "pred_126": 0.0,
            "pred_127": 0.0,
            "pred_146": 0.0,
            "pred_147": 0.0,
            "pred_148": 0.0,
            "pred_149": 0.0,
            "pred_150": 0.0,
            "pred_151": 0.0,
            "pred_234": 0.0,
            "pred_153": 0.0,
            "pred_154": 0.0,
            "pred_155": 0.0,
            "pred_156": 0.0,
            "pred_157": 0.0,
            "pred_158": 0.0,
            "pred_159": 0.0,
            "pred_160": 0.0,
            "pred_145": 0.0,
            "pred_144": 0.0,
            "pred_143": 0.0,
            "pred_134": 0.0,
            "pred_128": 0.0,
            "pred_129": 0.0,
            "pred_130": 0.0,
            "pred_131": 0.0,
            "pred_132": 0.0,
            "pred_133": 0.0,
            "pred_135": 0.0,
            "pred_142": 0.0,
            "pred_136": 0.0,
            "pred_137": 0.0,
            "pred_138": 0.0,
            "pred_139": 0.0,
            "pred_140": 0.0,
            "pred_141": 0.0,
            "pred_152": 0.0
        }
    }
}